hydromt_delwaq/__init__.py
hydromt_delwaq/delwaq.py
hydromt_delwaq/demission.py
hydromt_delwaq/utils.py
hydromt_delwaq/data/admin_bound/gadm_level1_mapping.csv
hydromt_delwaq/data/delwaq/emission_raster.csv
hydromt_delwaq/data/delwaq/emission_vector.csv
hydromt_delwaq/workflows/.gitkeep
hydromt_delwaq/workflows/__init__.py
hydromt_delwaq/workflows/config.py
hydromt_delwaq/workflows/emissions.py
hydromt_delwaq/workflows/forcing.py
hydromt_delwaq/workflows/geometry.py
hydromt_delwaq/workflows/roads.py
hydromt_delwaq/workflows/segments.py
hydromt_delwaq-0.3.1.dist-info/entry_points.txt
hydromt_delwaq-0.3.1.dist-info/licenses/LICENSE
hydromt_delwaq-0.3.1.dist-info/WHEEL
hydromt_delwaq-0.3.1.dist-info/METADATA
hydromt_delwaq-0.3.1.dist-info/RECORD
