Metadata-Version: 2.4
Name: hydromt_delwaq
Version: 0.3.1
Summary: hydroMT plugin for DELWAQ models.
Author-email: Hélène Boisgontier <helene.boisgontier@deltares.nl>, Sibren Loos <sibren.loos@deltares.nl>
Requires-Python: >=3.10
Classifier: Development Status :: 4 - Beta
Classifier: Intended Audience :: Developers
Classifier: Intended Audience :: Science/Research
Classifier: Topic :: Scientific/Engineering :: Hydrology
Classifier: License :: OSI Approved :: GNU General Public License v3 or later (GPLv3+)
Classifier: Programming Language :: Python :: 3
License-File: LICENSE
Requires-Dist: hydromt >=0.9.1,<0.11
Requires-Dist: hydromt_wflow >=0.5.0,<0.9
Requires-Dist: geopandas >=0.10
Requires-Dist: numpy
Requires-Dist: pandas
Requires-Dist: pyproj
Requires-Dist: rasterio
Requires-Dist: scipy
Requires-Dist: shapely
Requires-Dist: tqdm
Requires-Dist: xarray
Requires-Dist: xugrid >=0.14.3
Requires-Dist: black ; extra == "dev"
Requires-Dist: ruff ; extra == "dev"
Requires-Dist: pre-commit ; extra == "dev"
Requires-Dist: pip>=23.1.2 ; extra == "dev"
Requires-Dist: nbsphinx ; extra == "doc"
Requires-Dist: sphinx ; extra == "doc"
Requires-Dist: sphinx_design ; extra == "doc"
Requires-Dist: pydata-sphinx-theme ; extra == "doc"
Requires-Dist: sphinx_autosummary_accessors ; extra == "doc"
Requires-Dist: jupyterlab ; extra == "examples"
Requires-Dist: cartopy ; extra == "examples"
Requires-Dist: matplotlib ; extra == "examples"
Requires-Dist: notebook ; extra == "examples"
Requires-Dist: hydromt_delwaq[dev, test, doc, examples] ; extra == "full"
Requires-Dist: hydromt_delwaq[examples] ; extra == "slim"
Requires-Dist: pytest>=2.7.3 ; extra == "test"
Requires-Dist: pytest-cov ; extra == "test"
Requires-Dist: pytest-timeout ; extra == "test"
Project-URL: Documentation, https://deltares.github.io/hydromt_delwaq/latest/
Project-URL: Source, https://github.com/Deltares/hydromt_delwaq
Provides-Extra: dev
Provides-Extra: doc
Provides-Extra: examples
Provides-Extra: full
Provides-Extra: slim
Provides-Extra: test
